{"type":"FeatureCollection","features":[{"type":"Feature","geometry":{"type":"Point","coordinates":[4.9343517,52.3200157]},"properties":{"name":"Amsterdam Old Course","description":"","_styleId":"poiPin"}},{"type":"Feature","geometry":{"type":"Point","coordinates":[4.9553836,52.2850611]},"properties":{"name":"Golfbaan De Hoge Dijk","description":"","_styleId":"poiPin"}},{"type":"Feature","geometry":{"type":"Point","coordinates":[4.8063051,52.3393195]},"properties":{"name":"Golfbaan Sloten","description":"","_styleId":"poiPin"}},{"type":"Feature","geometry":{"type":"Point","coordinates":[4.7948688,52.3719203]},"properties":{"name":"Golfclub Ookmeer","description":"","_styleId":"poiPin"}}],"_styles":{"poiPin":{"iconUrl":"https://maps.google.com/mapfiles/kml/shapes/golf.png","iconScale":0.9},"cell":{"fillColor":"#32cd32","fillOpacity":0.188,"color":"#32cd32","opacity":1.0,"weight":1.0}}}